pareto_front/__init__.py
pareto_front-0.0.2.dist-info/METADATA
pareto_front-0.0.2.dist-info/WHEEL
pareto_front-0.0.2.dist-info/top_level.txt
pareto_front-0.0.2.dist-info/RECORD
